<?xml version="1.0" encoding="UTF-8"?>
<OfficeApp
  xmlns="http://schemas.microsoft.com/office/appforoffice/1.1"
  xmlns:xsi="http://www.w3.org/2001/XMLSchema-instance"
  xmlns:bt="http://schemas.microsoft.com/office/officeappbasictypes/1.0"
  xsi:type="TaskPaneApp">

  <Id>a1b2c3d4-e5f6-7890-abcd-ef1234567890</Id>
  <Version>1.0.0</Version>
  <ProviderName>OmniContext</ProviderName>
  <DefaultLocale>en-US</DefaultLocale>
  <DisplayName DefaultValue="OmniContext" />
  <Description DefaultValue="Connect Microsoft Office to OmniContext CLI, an AI coding assistant." />
  <IconUrl DefaultValue="{{BASE_URL}}/assets/icon-32.png" />
  <HighResolutionIconUrl DefaultValue="{{BASE_URL}}/assets/icon-80.png" />
  <SupportUrl DefaultValue="https://github.com/nicepkg/omni-context-cli" />

  <Hosts>
    <Host Name="Document" />
    <Host Name="Workbook" />
    <Host Name="Presentation" />
  </Hosts>

  <DefaultSettings>
    <SourceLocation DefaultValue="{{BASE_URL}}/taskpane.html" />
  </DefaultSettings>

  <Permissions>ReadWriteDocument</Permissions>

  <VersionOverrides xmlns="http://schemas.microsoft.com/office/taskpaneappversionoverrides" xsi:type="VersionOverridesV1_0">
    <Hosts>
      
      <Host xsi:type="Document">
        <DesktopFormFactor>
          <ExtensionPoint xsi:type="PrimaryCommandSurface">
            <OfficeTab id="TabHome">
              <Group id="OmxGroup.Word">
                <Label resid="GroupLabel" />
                <Icon>
                  <bt:Image size="16" resid="Icon.16" />
                  <bt:Image size="32" resid="Icon.32" />
                  <bt:Image size="80" resid="Icon.80" />
                </Icon>
                <Control xsi:type="Button" id="ShowTaskpane.Word">
                  <Label resid="TaskpaneButton.Label" />
                  <Supertip>
                    <Title resid="TaskpaneButton.Label" />
                    <Description resid="TaskpaneButton.Tooltip" />
                  </Supertip>
                  <Icon>
                    <bt:Image size="16" resid="Icon.16" />
                    <bt:Image size="32" resid="Icon.32" />
                    <bt:Image size="80" resid="Icon.80" />
                  </Icon>
                  <Action xsi:type="ShowTaskpane">
                    <TaskpaneId>OmxTaskpane</TaskpaneId>
                    <SourceLocation resid="Taskpane.Url" />
                  </Action>
                </Control>
              </Group>
            </OfficeTab>
          </ExtensionPoint>
        </DesktopFormFactor>
      </Host>
      <Host xsi:type="Workbook">
        <DesktopFormFactor>
          <ExtensionPoint xsi:type="PrimaryCommandSurface">
            <OfficeTab id="TabHome">
              <Group id="OmxGroup.Excel">
                <Label resid="GroupLabel" />
                <Icon>
                  <bt:Image size="16" resid="Icon.16" />
                  <bt:Image size="32" resid="Icon.32" />
                  <bt:Image size="80" resid="Icon.80" />
                </Icon>
                <Control xsi:type="Button" id="ShowTaskpane.Excel">
                  <Label resid="TaskpaneButton.Label" />
                  <Supertip>
                    <Title resid="TaskpaneButton.Label" />
                    <Description resid="TaskpaneButton.Tooltip" />
                  </Supertip>
                  <Icon>
                    <bt:Image size="16" resid="Icon.16" />
                    <bt:Image size="32" resid="Icon.32" />
                    <bt:Image size="80" resid="Icon.80" />
                  </Icon>
                  <Action xsi:type="ShowTaskpane">
                    <TaskpaneId>OmxTaskpane</TaskpaneId>
                    <SourceLocation resid="Taskpane.Url" />
                  </Action>
                </Control>
              </Group>
            </OfficeTab>
          </ExtensionPoint>
        </DesktopFormFactor>
      </Host>
      <Host xsi:type="Presentation">
        <DesktopFormFactor>
          <ExtensionPoint xsi:type="PrimaryCommandSurface">
            <OfficeTab id="TabHome">
              <Group id="OmxGroup.PowerPoint">
                <Label resid="GroupLabel" />
                <Icon>
                  <bt:Image size="16" resid="Icon.16" />
                  <bt:Image size="32" resid="Icon.32" />
                  <bt:Image size="80" resid="Icon.80" />
                </Icon>
                <Control xsi:type="Button" id="ShowTaskpane.PowerPoint">
                  <Label resid="TaskpaneButton.Label" />
                  <Supertip>
                    <Title resid="TaskpaneButton.Label" />
                    <Description resid="TaskpaneButton.Tooltip" />
                  </Supertip>
                  <Icon>
                    <bt:Image size="16" resid="Icon.16" />
                    <bt:Image size="32" resid="Icon.32" />
                    <bt:Image size="80" resid="Icon.80" />
                  </Icon>
                  <Action xsi:type="ShowTaskpane">
                    <TaskpaneId>OmxTaskpane</TaskpaneId>
                    <SourceLocation resid="Taskpane.Url" />
                  </Action>
                </Control>
              </Group>
            </OfficeTab>
          </ExtensionPoint>
        </DesktopFormFactor>
      </Host>
    </Hosts>

    <Resources>
      <bt:Images>
        <bt:Image id="Icon.16" DefaultValue="{{BASE_URL}}/assets/icon-16.png" />
        <bt:Image id="Icon.32" DefaultValue="{{BASE_URL}}/assets/icon-32.png" />
        <bt:Image id="Icon.80" DefaultValue="{{BASE_URL}}/assets/icon-80.png" />
      </bt:Images>
      <bt:Urls>
        <bt:Url id="Taskpane.Url" DefaultValue="{{BASE_URL}}/taskpane.html" />
      </bt:Urls>
      <bt:ShortStrings>
        <bt:String id="GroupLabel" DefaultValue="OmniContext" />
        <bt:String id="TaskpaneButton.Label" DefaultValue="OmniContext" />
      </bt:ShortStrings>
      <bt:LongStrings>
        <bt:String id="TaskpaneButton.Tooltip" DefaultValue="Open OmniContext AI assistant panel" />
      </bt:LongStrings>
    </Resources>
  </VersionOverrides>
</OfficeApp>
